ganesha_experimental/__init__.py
ganesha_experimental/main.py
Optimus_Prime-2.0.1.dist-info/LICENSE
Optimus_Prime-2.0.1.dist-info/METADATA
Optimus_Prime-2.0.1.dist-info/WHEEL
Optimus_Prime-2.0.1.dist-info/top_level.txt
Optimus_Prime-2.0.1.dist-info/RECORD
