Metadata-Version: 2.1
Name: Optimus-Prime
Version: 2.0.1
Summary: Prime number calculator
Home-page: https://github.com/awakzdev/CICD-PyPi-Artifact
Author: Elazar Chodjayev
Author-email: zenmyx@gmail.com
License: UNKNOWN
Platform: UNKNOWN
Classifier: Programming Language :: Python :: 3
Classifier: License :: OSI Approved :: MIT License
Classifier: Operating System :: OS Independent
